<?xml version="1.0" encoding="utf-8" ?>
<dwsync>
<file name="AbstractAssetsHelper.php" server="ftp.qualitiinternet.com.br//www/" local="131317255066407211" remote="131317198200000000" Dst="2" />
<file name="AssetHelper.php" server="ftp.qualitiinternet.com.br//www/" local="131317255066617224" remote="131317198200000000" Dst="2" />
<file name="CsrfProtectedRouteHelper.php" server="ftp.qualitiinternet.com.br//www/" local="131317255066987245" remote="131317198200000000" Dst="2" />
<file name="CsrfTokenInputHelper.php" server="ftp.qualitiinternet.com.br//www/" local="131317255067697285" remote="131317198200000000" Dst="2" />
<file name="CssAssetsHelper.php" server="ftp.qualitiinternet.com.br//www/" local="131317255067907297" remote="131317198200000000" Dst="2" />
<file name="FormatDateDiffHelper.php" server="ftp.qualitiinternet.com.br//www/" local="131317255068277318" remote="131317198200000000" Dst="2" />
<file name="FormatDateHelper.php" server="ftp.qualitiinternet.com.br//www/" local="131317255069157369" remote="131317198200000000" Dst="2" />
<file name="GeneratePaginationHelper.php" server="ftp.qualitiinternet.com.br//www/" local="131317255069057363" remote="131317198200000000" Dst="2" />
<file name="JsAssetsHelper.php" server="ftp.qualitiinternet.com.br//www/" local="131317255069767404" remote="131317198200000000" Dst="2" />
<file name="L10nHelper.php" server="ftp.qualitiinternet.com.br//www/" local="131317255070337436" remote="131317198200000000" Dst="2" />
<file name="RouteHelper.php" server="ftp.qualitiinternet.com.br//www/" local="131317255070377439" remote="131317198200000000" Dst="2" />
<file name="AbstractAssetsHelper.php" server="C:/xampp/htdocs/qualiti/" local="131317255060000000" remote="131317255060000000" Dst="1" />
<file name="AssetHelper.php" server="C:/xampp/htdocs/qualiti/" local="131317255060000000" remote="131317255060000000" Dst="1" />
<file name="CsrfProtectedRouteHelper.php" server="C:/xampp/htdocs/qualiti/" local="131317255060000000" remote="131317255060000000" Dst="1" />
<file name="CsrfTokenInputHelper.php" server="C:/xampp/htdocs/qualiti/" local="131317255060000000" remote="131317255060000000" Dst="1" />
<file name="CssAssetsHelper.php" server="C:/xampp/htdocs/qualiti/" local="131317255060000000" remote="131317255060000000" Dst="1" />
<file name="FormatDateDiffHelper.php" server="C:/xampp/htdocs/qualiti/" local="131317255060000000" remote="131317255060000000" Dst="1" />
<file name="FormatDateHelper.php" server="C:/xampp/htdocs/qualiti/" local="131317255060000000" remote="131317255060000000" Dst="1" />
<file name="GeneratePaginationHelper.php" server="C:/xampp/htdocs/qualiti/" local="131317255060000000" remote="131317255060000000" Dst="1" />
<file name="JsAssetsHelper.php" server="C:/xampp/htdocs/qualiti/" local="131317255060000000" remote="131317255060000000" Dst="1" />
<file name="L10nHelper.php" server="C:/xampp/htdocs/qualiti/" local="131317255070000000" remote="131317255070000000" Dst="1" />
<file name="RouteHelper.php" server="C:/xampp/htdocs/qualiti/" local="131317255070000000" remote="131317255070000000" Dst="1" />
</dwsync>